{
    "edges": [
        {
            "vertices": [
                {
                    "id": "2"
                },
                {
                    "id": "1"
                }
            ]
        },
        {
            "vertices": [
                {
                    "id": "4"
                },
                {
                    "id": "14"
                },
                {
                    "id": "2"
                }
            ]
        },
        {
            "vertices": [
                {
                    "id": "15"
                },
                {
                    "id": "2"
                }
            ]
        },
        {
            "vertices": [
                {
                    "id": "4"
                },
                {
                    "id": "15"
                }
            ]
        },
        {
            "vertices": [
                {
                    "id": "15"
                },
                {
                    "id": "5"
                },
                {
                    "id": "6"
                }
            ]
        },
        {
            "vertices": [
                {
                    "id": "15"
                },
                {
                    "id": "6"
                }
            ]
        },
        {
            "vertices": [
                {
                    "id": "3"
                },
                {
                    "id": "6"
                }
            ]
        }
    ],
    "vertices": [
        {
            "id": "133"
        }
    ]
}